flask_protobuf/__init__.py
flask_protobuf/extension.py
flask_protobuf-0.1.3.dist-info/LICENSE.txt
flask_protobuf-0.1.3.dist-info/METADATA
flask_protobuf-0.1.3.dist-info/WHEEL
flask_protobuf-0.1.3.dist-info/top_level.txt
flask_protobuf-0.1.3.dist-info/RECORD
