Metadata-Version: 2.1
Name: flask-protobuf
Version: 0.1.3
Summary: Flask-Protobuf is a Python package that provides integration between Flask and Protocol Buffers (protobuf). It allows you to easily handle incoming protobuf messages in your Flask application.
Home-page: https://github.com/Mackhintoshi/Flask-Protobuf
Author: Jerick Gutierrez
License: MIT
Keywords: flask,protobuf,google,protocol buffers
License-File: LICENSE.txt
Requires-Dist: Flask (>=2.3.2)
Requires-Dist: protobuf (>=3.17.3)
